[
    {
        "name": "Lil Pudgy",
        "quantity": 0.0,
        "platform": "opensea",
        "api_name_format": "lilpudgys",
        "token": "ETH",
        "token_floor_price": "0.75",
        "total$": 0,
        "vol_24": "0.86"
    },
    {
        "name": "Pudgy Rod",
        "quantity": 0.0,
        "platform": "opensea",
        "api_name_format": "pudgyrods",
        "token": "ETH",
        "token_floor_price": "0.19",
        "total$": 0,
        "vol_24": "-0.74"
    },
    {
        "name": "Holo Friends",
        "quantity": 0.0,
        "platform": "opensea",
        "api_name_format": "holofriendsnft",
        "token": "ETH",
        "token_floor_price": "0.25",
        "total$": 0,
        "vol_24": "0.00"
    },
    {
        "name": "Kitaro World",
        "quantity": 0.0,
        "platform": "coingecko",
        "api_name_format": "kitaroworld",
        "token": "ETH",
        "token_floor_price": "0.04",
        "total$": 0,
        "vol_24": "101.65"
    },
    {
        "name": "Plooshies",
        "quantity": 0,
        "platform": "opensea",
        "api_name_format": "theplooshies",
        "token": "ETH",
        "token_floor_price": "0.24",
        "total$": 0,
        "vol_24": "-0.67"
    },
    {
        "name": "Lil Buns",
        "quantity": 0.0,
        "platform": "opensea",
        "api_name_format": "hefty-presents",
        "token": "ETH",
        "token_floor_price": "0.01",
        "total$": 0,
        "vol_24": "0.00"
    },
    {
        "name": "BoDoggos",
        "quantity": 0.0,
        "platform": "magiceden",
        "api_name_format": "bodoggos",
        "token": "SOL",
        "token_floor_price": "1.99",
        "total$": 0,
        "vol_24": "0.00"
    },
    {
        "name": "Purrr Pals",
        "quantity": 0.0,
        "platform": "opensea",
        "api_name_format": "purrrpals",
        "token": "MATIC",
        "token_floor_price": "9.77",
        "total$": 0,
        "vol_24": "-0.40"
    }
]